{"name":"Tiny Daily Task Manager","tagline":"Tiny Daily Task Manager, a web application built on top of Extjs 4, Jquery and PHP 5. A free tasks management tool which works with man-hours unit instead of classical man-days.","body":"Tiny Daily Task Manager\r\n====================\r\n\r\nTDTM Roadmap\r\n--------------------------------------\r\n\r\n1. French translation & translation menu (<b>DONE</b>)\r\n2. Login system\r\n3. Documentation (PHP & Js)\r\n4. Allow clicking on calendar's tasks to edit them\r\n5. Filter by task\r\n\r\nTDTM requirements\r\n--------------------------------------\r\n\r\nWhat TDTM needs to work correctly ?\r\n###Client Side\r\n\t\r\n1. Extjs 4.2.1\r\n2. JsDuck 4.6.1\r\n3. Jquery 1.10.x\r\n4. FullCalendar 1.6.x (jquery plugin by Adam Shaw)\r\n\r\n\r\n###Browser compatibility\r\n1. Internet Explorer 6+\r\n2. Firefox 3.6+ (PC, Mac)\r\n3. Safari 4+\r\n4. Chrome 10+\r\n5. Opera 11+ (PC, Mac)\r\n\r\n###Server Side\r\n1. Any server language compatible with REST Api, default is PHP (5.2.3)\r\n2. Apache 2\r\n3. Mysql (or any storage system which respects TDTM data model)\r\n4. Be sure your web server accept all HTTP request (GET, POST, PUT, DELETE)\r\n\r\nTDTM contraints\r\n--------------------------------------\r\nTDTM works as a standalone and full screen interface.\r\nWe just need to launch a single Ext.application to manage all interfaces elements.\r\n\r\n\r\nTDTM technicals points\r\n--------------------------------------\r\n\r\n1. RESTFUL\r\nThis project is based on REST principles to allow a better communication between client side and server side.\r\nIt allows anyone to switch easily the entire server side without changing interface.\r\n\r\n2. Full Javascipt interface\r\nExtjs appears to be the better framework to create a thick client like application in a sort period of time.\r\nIt is fully compatible with a REST api.\r\n\r\n3. Full ajax application\r\nThis project works as a standalone thick client. Furthermore an ajax application implies to not refresh all the page everytime a request is sent.\r\nWe just need to refresh a part of our application (what Extjs do perfectly).\r\n\r\nTDTM features\r\n--------------------------------------\r\n\r\n1. CRUD Projects\r\n2. CRUD Members\r\n3. CRUD Task\r\n4. Display a week calendar\r\n5. Allow task or member filtering on calendar event\r\n","google":"","note":"Don't delete this file! It's used internally to help with page regeneration."}